datacreator/__init__.py
datacreator/creator.py
algo_trading_data_creator-0.1.0.dist-info/METADATA
algo_trading_data_creator-0.1.0.dist-info/WHEEL
algo_trading_data_creator-0.1.0.dist-info/top_level.txt
algo_trading_data_creator-0.1.0.dist-info/RECORD
