Metadata-Version: 2.4
Name: algo_trading_data_creator
Version: 0.1.0
Summary: A small utility for fetching and formatting data from SQL Server using GetKlineData2 db function.
Author-email: Okan Uregen <okanuregen@gmail.com>
Requires-Python: >=3.7
Requires-Dist: pymssql
Requires-Dist: pandas
